ftmq_search/__init__.py
ftmq_search/cli.py
ftmq_search/exceptions.py
ftmq_search/logging.py
ftmq_search/logic.py
ftmq_search/model.py
ftmq_search/settings.py
ftmq_search/store/__init__.py
ftmq_search/store/base.py
ftmq_search/store/elastic/mapping.py
ftmq_search/store/elastic/query.py
ftmq_search/store/elastic/store.py
ftmq_search/store/sqlite.py
ftmq_search/store/tantivy.py
ftmq_search-0.0.4.dist-info/LICENSE
ftmq_search-0.0.4.dist-info/METADATA
ftmq_search-0.0.4.dist-info/WHEEL
ftmq_search-0.0.4.dist-info/entry_points.txt
ftmq_search-0.0.4.dist-info/RECORD
