Metadata-Version: 2.3
Name: ftmq-search
Version: 0.0.4
Summary: followthemoney data search experiments based on ftmq
License: AGPLv3+
Author: Simon Wörpel
Author-email: simon.woerpel@pm.me
Requires-Python: >=3.11,<4
Classifier: Intended Audience :: Developers
Classifier: Operating System :: OS Independent
Classifier: Programming Language :: Python
Classifier: Programming Language :: Python :: 3.11
Classifier: Programming Language :: Python :: 3.12
Classifier: Programming Language :: Python :: 3.13
Provides-Extra: elasticsearch
Provides-Extra: tantivy
Requires-Dist: elasticsearch (>8,<9) ; extra == "elasticsearch"
Requires-Dist: ftmq (>=0.8.3,<0.9.0)
Requires-Dist: tantivy (>=0.24.0,<0.25.0) ; extra == "tantivy"
Project-URL: Documentation, https://github.com/dataresearchcenter/ftmq-search
Project-URL: Homepage, https://github.com/dataresearchcenter/ftmq-search
Project-URL: Issues, https://github.com/dataresearchcenter/ftmq-search/issues
Project-URL: Repository, https://github.com/dataresearchcenter/ftmq-search
